automox_mcp/__init__.py
automox_mcp/client.py
automox_mcp/py.typed
automox_mcp/schemas.py
automox_mcp/server.py
automox_mcp/resources/__init__.py
automox_mcp/resources/policy_resources.py
automox_mcp/resources/servergroup_resources.py
automox_mcp/tools/__init__.py
automox_mcp/tools/account_tools.py
automox_mcp/tools/audit_tools.py
automox_mcp/tools/device_tools.py
automox_mcp/tools/policy_tools.py
automox_mcp/utils/__init__.py
automox_mcp/utils/organization.py
automox_mcp/utils/tooling.py
automox_mcp/workflows/__init__.py
automox_mcp/workflows/account.py
automox_mcp/workflows/audit.py
automox_mcp/workflows/devices.py
automox_mcp/workflows/policy.py
automox_mcp-0.1.0.dist-info/licenses/LICENSE
automox_mcp-0.1.0.dist-info/METADATA
automox_mcp-0.1.0.dist-info/WHEEL
automox_mcp-0.1.0.dist-info/entry_points.txt
automox_mcp-0.1.0.dist-info/top_level.txt
automox_mcp-0.1.0.dist-info/RECORD
