Metadata-Version: 2.4
Name: automox-mcp
Version: 0.1.0
Summary: An MCP server implementation for Automox
Author: Automox
License-Expression: MIT
Project-URL: Homepage, https://github.com/AutomoxCommunity/automox-mcp
Project-URL: Repository, https://github.com/AutomoxCommunity/automox-mcp
Project-URL: Issues, https://github.com/AutomoxCommunity/automox-mcp/issues
Project-URL: Documentation, https://github.com/AutomoxCommunity/automox-mcp#readme
Classifier: Development Status :: 4 - Beta
Classifier: Intended Audience :: System Administrators
Classifier: Operating System :: OS Independent
Classifier: Programming Language :: Python :: 3
Classifier: Programming Language :: Python :: 3.11
Classifier: Programming Language :: Python :: 3.12
Classifier: Programming Language :: Python :: 3.13
Classifier: Topic :: System :: Systems Administration
Requires-Python: >=3.11
License-File: LICENSE
Requires-Dist: fastmcp>=2.0.0
Requires-Dist: httpx>=0.28
Requires-Dist: pydantic>=2.12
Requires-Dist: python-dotenv>=1.1
Provides-Extra: dev
Requires-Dist: pytest>=8.2; extra == "dev"
Requires-Dist: pytest-asyncio>=0.23; extra == "dev"
Requires-Dist: ruff>=0.4; extra == "dev"
Requires-Dist: mypy>=1.9; extra == "dev"
Requires-Dist: build>=1.2.2; extra == "dev"
Requires-Dist: twine>=5.1; extra == "dev"
Dynamic: license-file
